configurations/wsgi.py
configurations/importer.py
configurations/values.py
configurations/decorators.py
configurations/fastcgi.py
configurations/utils.py
configurations/__init__.py
configurations/base.py
configurations/management.py
django_configurations_x-0.8.2.dist-info/metadata.json
django_configurations_x-0.8.2.dist-info/top_level.txt
django_configurations_x-0.8.2.dist-info/METADATA
django_configurations_x-0.8.2.dist-info/WHEEL
django_configurations_x-0.8.2.dist-info/pbr.json
django_configurations_x-0.8.2.dist-info/RECORD
django_configurations_x-0.8.2.dist-info/entry_points.txt
django_configurations_x-0.8.2.dist-info/DESCRIPTION.rst
