Metadata-Version: 2.0
Name: django-configurations-x
Version: 0.8.2
Summary: A helper for organizing Django settings.
Home-page: http://django-configurations.readthedocs.org/
Author: Jannis Leidel
Author-email: jannis@leidel.info
License: BSD
Platform: UNKNOWN
Classifier: Development Status :: 4 - Beta
Classifier: Framework :: Django
Classifier: Intended Audience :: Developers
Classifier: License :: OSI Approved :: BSD License
Classifier: Operating System :: OS Independent
Classifier: Programming Language :: Python
Classifier: Programming Language :: Python :: 2.6
Classifier: Programming Language :: Python :: 2.7
Classifier: Programming Language :: Python :: 3.2
Classifier: Programming Language :: Python :: 3.3
Classifier: Topic :: Utilities
